my_happy_flow/__init__.py
my_happy_flow/_version.py
my_happy_flow/version.py
my_happy_flow/core/__init__.py
my_happy_flow/core/job.py
my_happy_flow/pandas/__init__.py
my_happy_flow/pandas/happy_pandas.py
my_happy_flow-0.0.57.dist-info/LICENSE
my_happy_flow-0.0.57.dist-info/METADATA
my_happy_flow-0.0.57.dist-info/WHEEL
my_happy_flow-0.0.57.dist-info/top_level.txt
my_happy_flow-0.0.57.dist-info/RECORD
