Metadata-Version: 2.1
Name: my-happy-flow
Version: 0.0.57
Summary: From data to information. Peformance first with easy use.
Home-page: https://github.com/ggservice007/my-happy-flow
Author: ggservice007
Author-email: ggservice007@126.com
License: Apache 2
Platform: UNKNOWN
Requires-Python: >=3.7.7
Requires-Dist: ray (>=1.1.0)
Requires-Dist: modin (>=0.8.3)
